openaiunlimitedfun/__init__.py
openaiunlimitedfun/utils.py
openaiunlimitedfun-0.1.1.dist-info/LICENSE
openaiunlimitedfun-0.1.1.dist-info/METADATA
openaiunlimitedfun-0.1.1.dist-info/WHEEL
openaiunlimitedfun-0.1.1.dist-info/top_level.txt
openaiunlimitedfun-0.1.1.dist-info/RECORD
