Metadata-Version: 2.1
Name: openaiunlimitedfun
Version: 0.1.1
Summary: A comprehensive wrapper for the OpenAI API, facilitating seamless interaction with GPT models. Features include conversation management, dynamic function execution, and tools for creating JSON schemas for function descriptions. Simplifies setting API keys and managing chat contexts for enhanced GPT-based applications.
Home-page: https://github.com/maestromaximo/OpenAiUnlimitedFuncWrapper
Author: Alejandro Garcia Polo
Author-email: alejandrogarcia2423@hotmail.com
Keywords: openai,api,wrapper,function_calling,vectors,pseudo_func
Classifier: Development Status :: 3 - Alpha
Classifier: Intended Audience :: Developers
Classifier: Topic :: Software Development :: Libraries
Classifier: License :: OSI Approved :: MIT License
Classifier: Programming Language :: Python :: 3
Classifier: Programming Language :: Python :: 3.6
Classifier: Programming Language :: Python :: 3.7
Classifier: Programming Language :: Python :: 3.8
Classifier: Programming Language :: Python :: 3.9
Classifier: Programming Language :: Python :: 3.10
Classifier: Programming Language :: Python :: 3.11
Classifier: Programming Language :: Python :: 3.12
Requires-Python: >=3.6
License-File: LICENSE
Requires-Dist: annotated-types (==0.6.0)
Requires-Dist: anyio (==4.2.0)
Requires-Dist: certifi (==2023.11.17)
Requires-Dist: charset-normalizer (==3.3.2)
Requires-Dist: colorama (==0.4.6)
Requires-Dist: distro (==1.9.0)
Requires-Dist: h11 (==0.14.0)
Requires-Dist: httpcore (==1.0.2)
Requires-Dist: httpx (==0.26.0)
Requires-Dist: idna (==3.6)
Requires-Dist: numpy (==1.26.3)
Requires-Dist: openai (==1.6.1)
Requires-Dist: pandas (==2.1.4)
Requires-Dist: pydantic (==2.5.3)
Requires-Dist: pydantic-core (==2.14.6)
Requires-Dist: python-dateutil (==2.8.2)
Requires-Dist: python-dotenv (==1.0.0)
Requires-Dist: pytz (==2023.3.post1)
Requires-Dist: regex (==2023.12.25)
Requires-Dist: requests (==2.31.0)
Requires-Dist: six (==1.16.0)
Requires-Dist: sniffio (==1.3.0)
Requires-Dist: tenacity (==8.2.3)
Requires-Dist: tiktoken (==0.5.2)
Requires-Dist: tqdm (==4.66.1)
Requires-Dist: typing-extensions (==4.9.0)
Requires-Dist: tzdata (==2023.4)
Requires-Dist: urllib3 (==2.1.0)
